groundmag/DateToYear.py
groundmag/GetData.py
groundmag/GetStationInfo.py
groundmag/Globals.py
groundmag/PlotChain.py
groundmag/PlotData.py
groundmag/PlotPolarization.py
groundmag/PlotPolarizationChain.py
groundmag/PlotSpectrogram.py
groundmag/PlotSpectrogramChain.py
groundmag/PlotSpectrum.py
groundmag/ReadData.py
groundmag/Spectrogram.py
groundmag/Spectrogram3D.py
groundmag/Spectrum.py
groundmag/UTPlotLabel.py
groundmag/_PopulateStations.py
groundmag/_ReadBinary.py
groundmag/_ReadStations.py
groundmag/__init__.py
groundmag/hdz2xyz.py
groundmag/xyz2hdz.py
groundmag/__data/carisma.list
groundmag/__data/image.list
groundmag/__data/intermagnet.list
groundmag/__data/supermag.list
groundmag-0.0.1.dist-info/LICENSE
groundmag-0.0.1.dist-info/METADATA
groundmag-0.0.1.dist-info/WHEEL
groundmag-0.0.1.dist-info/top_level.txt
groundmag-0.0.1.dist-info/RECORD
