Metadata-Version: 2.1
Name: groundmag
Version: 0.0.1
Summary: A small package designed for reading ground magnetometer data.
Home-page: https://github.com/mattkjames7/groundmag
Author: Matthew Knight James
Author-email: mattkjames7@gmail.com
License: UNKNOWN
Platform: UNKNOWN
Classifier: Programming Language :: Python :: 3
Classifier: License :: OSI Approved :: GNU General Public License (GPL)
Classifier: Operating System :: POSIX
Requires-Dist: numpy
Requires-Dist: matplotlib
Requires-Dist: DateTimeTools
Requires-Dist: aacgmv2
Requires-Dist: pyIGRF
Requires-Dist: wavespec
Requires-Dist: RecarrayTools
Requires-Dist: PyFileIO
